fail_importing/__init__.py
fail_importing-1.0.0.dist-info/LICENSE.txt
fail_importing-1.0.0.dist-info/METADATA
fail_importing-1.0.0.dist-info/WHEEL
fail_importing-1.0.0.dist-info/top_level.txt
fail_importing-1.0.0.dist-info/RECORD
