Metadata-Version: 2.1
Name: fail-importing
Version: 1.0.0
Summary: A decorator designed to make testing optional dependencies painless.
Home-page: https://github.com/Tom01098/fail_importing
Author: Tom Humphreys
Author-email: Tom01098Code@gmail.com
License: MIT
Project-URL: Repo, https://github.com/Tom01098/fail_importing
Project-URL: Issues, https://github.com/Tom01098/fail_importing/issues
Platform: UNKNOWN
Classifier: Development Status :: 5 - Production/Stable
Classifier: License :: OSI Approved :: MIT License
Classifier: Programming Language :: Python :: 3.6
Classifier: Programming Language :: Python :: 3.7
Classifier: Programming Language :: Python :: 3.8
Classifier: Programming Language :: Python :: 3.9
Classifier: Programming Language :: Python :: Implementation :: CPython
Classifier: Topic :: Software Development :: Testing
Classifier: Topic :: Software Development :: Testing :: Unit
Requires-Python: >=3.6
License-File: LICENSE.txt
